{"observations":[{"target_id":"microsoft/resnet-18","tipo_target":"model","observation_type":"presence","observed_at":"2026-04-26T21:01:34.667612+00:00","source":"autonomous_observer","method":"oracle_hf_card"},{"target_id":"OpenMed/OpenMed-NER-PharmaDetect-SuperMedical-125M","tipo_target":"model","observation_type":"presence","observed_at":"2026-04-26T21:01:32.929978+00:00","source":"autonomous_observer","method":"oracle_hf_card"},{"target_id":"mistralai/Mistral-7B-v0.1","tipo_target":"model","observation_type":"absence","observed_at":"2026-04-26T21:01:31.200754+00:00","source":"autonomous_observer","method":"oracle_hf_card"},{"target_id":"unsloth/Llama-4-Scout-17B-16E-Instruct-GGUF","tipo_target":"model","observation_type":"presence","observed_at":"2026-04-26T21:01:29.510572+00:00","source":"autonomous_observer","method":"oracle_hf_card"},{"target_id":"nvidia/NVIDIA-Nemotron-Nano-9B-v2","tipo_target":"model","observation_type":"presence","observed_at":"2026-04-26T21:01:27.758167+00:00","source":"autonomous_observer","method":"oracle_hf_card"},{"target_id":"facebook/wav2vec2-base","tipo_target":"model","observation_type":"presence","observed_at":"2026-04-26T21:01:26.026518+00:00","source":"autonomous_observer","method":"oracle_hf_card"},{"target_id":"myendless/ManipDreamer3D_data","tipo_target":"dataset","observation_type":"absence","observed_at":"2026-04-26T21:01:24.175415+00:00","source":"autonomous_observer","method":"oracle_hf_card"},{"target_id":"facebook/opt-125m","tipo_target":"model","observation_type":"presence","observed_at":"2026-04-26T21:01:20.791301+00:00","source":"autonomous_observer","method":"oracle_hf_card"},{"target_id":"tohoku-nlp/bert-base-japanese-char","tipo_target":"model","observation_type":"presence","observed_at":"2026-04-26T21:01:19.067029+00:00","source":"autonomous_observer","method":"oracle_hf_card"},{"target_id":"xinsir/controlnet-union-sdxl-1.0","tipo_target":"model","observation_type":"absence","observed_at":"2026-04-26T21:01:17.334089+00:00","source":"autonomous_observer","method":"oracle_hf_card"},{"target_id":"google-bert/bert-base-multilingual-cased","tipo_target":"model","observation_type":"presence","observed_at":"2026-04-26T21:01:15.611966+00:00","source":"autonomous_observer","method":"oracle_hf_card"},{"target_id":"lmstudio-community/NVIDIA-Nemotron-3-Nano-30B-A3B-MLX-4bit","tipo_target":"model","observation_type":"presence","observed_at":"2026-04-26T21:01:13.867233+00:00","source":"autonomous_observer","method":"oracle_hf_card"},{"target_id":"SpatialVID/SpatialVID","tipo_target":"dataset","observation_type":"absence","observed_at":"2026-04-26T21:01:12.139677+00:00","source":"autonomous_observer","method":"oracle_hf_card"},{"target_id":"atom-in-the-universe/libgen-10k-1000k","tipo_target":"dataset","observation_type":"absence","observed_at":"2026-04-26T21:01:09.819794+00:00","source":"autonomous_observer","method":"oracle_hf_card"},{"target_id":"Bingsu/yolo-world-mirror","tipo_target":"model","observation_type":"absence","observed_at":"2026-04-26T21:01:06.469255+00:00","source":"autonomous_observer","method":"oracle_hf_card"},{"target_id":"docling-project/docling-layout-heron","tipo_target":"model","observation_type":"absence","observed_at":"2026-04-26T21:01:04.698157+00:00","source":"autonomous_observer","method":"oracle_hf_card"},{"target_id":"facebook/dinov2-giant","tipo_target":"model","observation_type":"absence","observed_at":"2026-04-26T21:01:02.957824+00:00","source":"autonomous_observer","method":"oracle_hf_card"},{"target_id":"prithivida/parrot_paraphraser_on_T5","tipo_target":"model","observation_type":"absence","observed_at":"2026-04-26T21:01:01.206874+00:00","source":"autonomous_observer","method":"oracle_hf_card"},{"target_id":"chonkie-ai/recipes","tipo_target":"dataset","observation_type":"absence","observed_at":"2026-04-26T21:00:59.537112+00:00","source":"autonomous_observer","method":"oracle_hf_card"},{"target_id":"timm/convnextv2_pico.fcmae_ft_in1k","tipo_target":"model","observation_type":"presence","observed_at":"2026-04-26T21:00:57.908927+00:00","source":"autonomous_observer","method":"oracle_hf_card"}],"count":20,"limit":20,"timestamp":"2026-04-26T21:15:03.059646Z"}